{
  "sourceDataInfo": {
    "newsID": "ET_M13_167153",
    "newsCategory": "연예",
    "newsSubcategory": "방송",
    "newsTitle": "‘연참3’ 과거진행형 사랑하고 있는 그[간밤TV]",
    "newsSubTitle": "",
    "newsContent": "과거 고민녀를 짝사랑했던 남친은 고민녀의 현재보다 과거를 더 사랑하고 있었다.\n지난 9일 방송된 KBS Joy 예능프로그램 ‘연애의 참견3’ 97회에서는 학창시절 이후 13년 만에 재회한 두 남녀의 사연이 소개됐다.\n고민녀는 학창시절 여신으로 불렸지만 현재는 역변한 상태였다.\n과거 고민녀를 짝사랑했던 친구는 성공한 CEO가 되었고, 친구의 고백으로 두 사람은 13년 만에 연인이 되었다.\n하지만 남친은 고민녀의 현재 모습 대신 과거 모습이 담긴 사진을 더 좋아했고, 피부 관리 이용권과 어린 시절 입던 옷까지 선물하며 과거로 돌아가길 바랐다.\n이에 주우재는 남친이 고민녀에게 고백한 이유로 “긁어본 복권인 거다. 조금만 관리하면 예전 모습으로 돌아갈 거라는 기대감을 갖고 있는 게 아닐까”라고 짐작했다.\n이후 고민녀는 과거 자신에게 보낸 남친의 고백 메일을 우연히 본 후 그의 마음이 진심이라고 확인하는데, 벅찬 마음도 잠시 친구에게 고민녀와의 연애를 우월감이라고 표현하는 남친의 말을 듣게 됐다.\n남친은 과거 고민녀를 좋아하던 수많은 남자들을 자신이 이긴 거라고 생각한다는 것이었다.\n크게 상처받은 고민녀는 현재의 나를 좋아하는 게 맞냐고 남친에게 묻는데, 남친은 모든 사실을 인정하면서 지금의 고민녀를 사랑할 수 있게 기회를 달라고 부탁했다.\n한혜진은 “고민녀의 리즈 시절을 인정해주는 남자를 만났다. 좋다. 하지만 현재의 나를 봐주는 연애를 해야 한다. 외모를 지적하는 사람과 관계를 유지한다? 절대적으로 타협할 수 없다”라는 의견을 전했다.\n곽정은은 “고민녀 역시 관심 없었던 친구가 번듯한 CEO로 나타났을 때 마음이 혹했다면 별반 다를 게 없다. 그것보다 앞으로 두 사람에게 어떤 일이 벌어졌을 때 어떻게 대처하는지를 봐야 한다”라고 충고했다.\n서장훈은 “애매하다. 남친 입장에선 과거 너무 좋아했던 사람인데 옛날 같지 않으니까 아쉬움을 내비치고 있다. 여기에 다른 남자들을 다 이긴 거라고 생각하고 있다. 순수함과 우월감이 뒤섞여있다. 명확하게 사랑인지 정확하게 못 찾고 있는 것 같다”라고 판단했고, 김숙은 “두 사람은 고등학교 때 알았지만 지금은 아는 게 거의 없다. 만난지 얼마 되지도 않았다. 여유롭게 알아가라”라고 조언했다.\n한편, KBS Joy ‘연애의 참견3’는 매주 화요일 밤 9시 30분에 방송된다.\nKBS Joy는 Skylife 1번, SK Btv 80번, LG U+tv 1번, KT olleh tv 41번 그리고 KBS 모바일 앱 ‘my K’에서 시청할 수 있으며, 지역별 케이블 채널 번호는 KBS N 홈페이지에서 확인할 수 있다. ‘연애의 참견3’의 더 많은 영상은 주요 온라인 채널(유튜브, 페이스북 등) 및 포털 사이트에서도 찾아볼 수 있다.",
    "partNum": "P1",
    "useType": 0,
    "processType": "D",
    "processPattern": "11",
    "processLevel": "하",
    "sentenceCount": 14,
    "sentenceInfo": [
      {
        "sentenceNo": 1,
        "sentenceContent": "과거 고민녀를 짝사랑했던 남친은 고민녀의 현재보다 과거를 더 사랑하고 있었다.",
        "sentenceSize": 43
      },
      {
        "sentenceNo": 2,
        "sentenceContent": "지난 9일 방송된 KBS Joy 예능프로그램 ‘연애의 참견3’ 97회에서는 학창시절 이후 13년 만에 재회한 두 남녀의 사연이 소개됐다.",
        "sentenceSize": 76
      },
      {
        "sentenceNo": 3,
        "sentenceContent": "고민녀는 학창시절 여신으로 불렸지만 현재는 역변한 상태였다.",
        "sentenceSize": 33
      },
      {
        "sentenceNo": 4,
        "sentenceContent": "과거 고민녀를 짝사랑했던 친구는 성공한 CEO가 되었고, 친구의 고백으로 두 사람은 13년 만에 연인이 되었다.",
        "sentenceSize": 62
      },
      {
        "sentenceNo": 5,
        "sentenceContent": "하지만 남친은 고민녀의 현재 모습 대신 과거 모습이 담긴 사진을 더 좋아했고, 피부 관리 이용권과 어린 시절 입던 옷까지 선물하며 과거로 돌아가길 바랐다.",
        "sentenceSize": 86
      },
      {
        "sentenceNo": 6,
        "sentenceContent": "이에 주우재는 남친이 고민녀에게 고백한 이유로 “긁어본 복권인 거다. 조금만 관리하면 예전 모습으로 돌아갈 거라는 기대감을 갖고 있는 게 아닐까”라고 짐작했다.",
        "sentenceSize": 89
      },
      {
        "sentenceNo": 7,
        "sentenceContent": "이후 고민녀는 과거 자신에게 보낸 남친의 고백 메일을 우연히 본 후 그의 마음이 진심이라고 확인하는데, 벅찬 마음도 잠시 친구에게 고민녀와의 연애를 우월감이라고 표현하는 남친의 말을 듣게 됐다.",
        "sentenceSize": 108
      },
      {
        "sentenceNo": 8,
        "sentenceContent": "남친은 과거 고민녀를 좋아하던 수많은 남자들을 자신이 이긴 거라고 생각한다는 것이었다.",
        "sentenceSize": 48
      },
      {
        "sentenceNo": 9,
        "sentenceContent": "크게 상처받은 고민녀는 현재의 나를 좋아하는 게 맞냐고 남친에게 묻는데, 남친은 모든 사실을 인정하면서 지금의 고민녀를 사랑할 수 있게 기회를 달라고 부탁했다.",
        "sentenceSize": 89
      },
      {
        "sentenceNo": 10,
        "sentenceContent": "한혜진은 “고민녀의 리즈 시절을 인정해주는 남자를 만났다. 좋다. 하지만 현재의 나를 봐주는 연애를 해야 한다. 외모를 지적하는 사람과 관계를 유지한다? 절대적으로 타협할 수 없다”라는 의견을 전했다.",
        "sentenceSize": 112
      },
      {
        "sentenceNo": 11,
        "sentenceContent": "곽정은은 “고민녀 역시 관심 없었던 친구가 번듯한 CEO로 나타났을 때 마음이 혹했다면 별반 다를 게 없다. 그것보다 앞으로 두 사람에게 어떤 일이 벌어졌을 때 어떻게 대처하는지를 봐야 한다”라고 충고했다.",
        "sentenceSize": 115
      },
      {
        "sentenceNo": 12,
        "sentenceContent": "서장훈은 “애매하다. 남친 입장에선 과거 너무 좋아했던 사람인데 옛날 같지 않으니까 아쉬움을 내비치고 있다. 여기에 다른 남자들을 다 이긴 거라고 생각하고 있다. 순수함과 우월감이 뒤섞여있다. 명확하게 사랑인지 정확하게 못 찾고 있는 것 같다”라고 판단했고, 김숙은 “두 사람은 고등학교 때 알았지만 지금은 아는 게 거의 없다. 만난지 얼마 되지도 않았다. 여유롭게 알아가라”라고 조언했다.",
        "sentenceSize": 218
      },
      {
        "sentenceNo": 13,
        "sentenceContent": "한편, KBS Joy ‘연애의 참견3’는 매주 화요일 밤 9시 30분에 방송된다.",
        "sentenceSize": 45
      },
      {
        "sentenceNo": 14,
        "sentenceContent": "KBS Joy는 Skylife 1번, SK Btv 80번, LG U+tv 1번, KT olleh tv 41번 그리고 KBS 모바일 앱 ‘my K’에서 시청할 수 있으며, 지역별 케이블 채널 번호는 KBS N 홈페이지에서 확인할 수 있다. ‘연애의 참견3’의 더 많은 영상은 주요 온라인 채널(유튜브, 페이스북 등) 및 포털 사이트에서도 찾아볼 수 있다.",
        "sentenceSize": 197
      }
    ]
  },
  "labeledDataInfo": {
    "newTitle": "'연참 3', 연애를 우월감이라 하는 남자 친구... 그들의 문제는?",
    "clickbaitClass": 0,
    "referSentenceInfo": [
      {
        "sentenceNo": 1,
        "referSentenceyn": "N"
      },
      {
        "sentenceNo": 2,
        "referSentenceyn": "N"
      },
      {
        "sentenceNo": 3,
        "referSentenceyn": "N"
      },
      {
        "sentenceNo": 4,
        "referSentenceyn": "N"
      },
      {
        "sentenceNo": 5,
        "referSentenceyn": "N"
      },
      {
        "sentenceNo": 6,
        "referSentenceyn": "N"
      },
      {
        "sentenceNo": 7,
        "referSentenceyn": "Y"
      },
      {
        "sentenceNo": 8,
        "referSentenceyn": "Y"
      },
      {
        "sentenceNo": 9,
        "referSentenceyn": "N"
      },
      {
        "sentenceNo": 10,
        "referSentenceyn": "N"
      },
      {
        "sentenceNo": 11,
        "referSentenceyn": "N"
      },
      {
        "sentenceNo": 12,
        "referSentenceyn": "N"
      },
      {
        "sentenceNo": 13,
        "referSentenceyn": "N"
      },
      {
        "sentenceNo": 14,
        "referSentenceyn": "N"
      }
    ]
  }
}