{
  "sourceDataInfo": {
    "newsID": "ET_M03_172992",
    "newsCategory": "연예",
    "newsSubcategory": "연예가화제",
    "newsTitle": "넥센 두산 준PO 3차전 승자는? … 유희관은 끝내 조기 강판",
    "newsSubTitle": "",
    "newsContent": "'넥센 두산 준플레이오프 3차전' '유희관 조기 강판' 13일 오후 서울 목동야구장에서 넥센과 두산의 2015 KBO 포스트시즌 준플레이오프 3차전이 열리고 있는 가운데, 두산 좌완 유희관(25)이 홈런포 두 방을 얻어맞고 조기 강판됐다.\n유희관은 13일 목동구장에서 열린 두산 넥센 준플레이오프(5전 3선승제) 3차전에서 선발 등판해 4이닝 3실점하고 마운드를 내려왔다.\n이날 등판을 앞둔 유희관은 많은 우려 속에 등판했다.\n올해 정규리그 30경기에 등판해 18승5패 평균자책점 3.94로 두산의 에이스 역할을 톡톡히 해냈다.\n그러나 후반기가 좋지 않았다.\n특히, 9월 이후 치른 6경기에서 2승1패, 평균자책점 8.89로 부진했다.\n올해 넥센전 성적은 1승1패 평균자책점 7.64. 우려에 부응하듯 유희관은 3회말부터 넥센의 방망이에 혼쭐났다.\n1,2회 주자를 내보내고도 후속타를 잘 막은 유희관은 0-0이던 3회말 1사에서 상대 2번타자 서건창에게 중월 솔로포를 얻어맞고 첫 실점했다.\n이어 4회말에는 2사에서 김하성에게 밋밋한 체인지업을 던졌으나 중월 솔로포를 허용했다.\n5회 마운드에 오른 유희관은 첫 타자 박병호에게 좌전 안타를 맞은 뒤 노경은으로 교체됐다.\n이날 유희관은 넥센 타선에 무려 7피안타(2피홈런)를 내줬다.\n볼넷은 3개. 5회 이어 던진 노경은이 계속된 1사 1,3루의 위기에서 김민성에게 좌익수 희생플라이를 헌납했고, 유희관의 실점은 3점이 됐다.\n오후 9시 현재 넥센이 5-0으로 앞서고 있으며, 현재 두산은 오현택이 바통을 이어받았다. '넥센 두산 준플레이오프 3차전' '유희관 조기 강판' 온라인 중앙일보",
    "partNum": "P1",
    "useType": 0,
    "processType": "D",
    "processPattern": "12",
    "processLevel": "하",
    "sentenceCount": 13,
    "sentenceInfo": [
      {
        "sentenceNo": 1,
        "sentenceContent": "'넥센 두산 준플레이오프 3차전' '유희관 조기 강판' 13일 오후 서울 목동야구장에서 넥센과 두산의 2015 KBO 포스트시즌 준플레이오프 3차전이 열리고 있는 가운데, 두산 좌완 유희관(25)이 홈런포 두 방을 얻어맞고 조기 강판됐다.",
        "sentenceSize": 133
      },
      {
        "sentenceNo": 2,
        "sentenceContent": "유희관은 13일 목동구장에서 열린 두산 넥센 준플레이오프(5전 3선승제) 3차전에서 선발 등판해 4이닝 3실점하고 마운드를 내려왔다.",
        "sentenceSize": 74
      },
      {
        "sentenceNo": 3,
        "sentenceContent": "이날 등판을 앞둔 유희관은 많은 우려 속에 등판했다.",
        "sentenceSize": 29
      },
      {
        "sentenceNo": 4,
        "sentenceContent": "올해 정규리그 30경기에 등판해 18승5패 평균자책점 3.94로 두산의 에이스 역할을 톡톡히 해냈다.",
        "sentenceSize": 56
      },
      {
        "sentenceNo": 5,
        "sentenceContent": "그러나 후반기가 좋지 않았다.",
        "sentenceSize": 16
      },
      {
        "sentenceNo": 6,
        "sentenceContent": "특히, 9월 이후 치른 6경기에서 2승1패, 평균자책점 8.89로 부진했다.",
        "sentenceSize": 42
      },
      {
        "sentenceNo": 7,
        "sentenceContent": "올해 넥센전 성적은 1승1패 평균자책점 7.64. 우려에 부응하듯 유희관은 3회말부터 넥센의 방망이에 혼쭐났다.",
        "sentenceSize": 62
      },
      {
        "sentenceNo": 8,
        "sentenceContent": "1,2회 주자를 내보내고도 후속타를 잘 막은 유희관은 0-0이던 3회말 1사에서 상대 2번타자 서건창에게 중월 솔로포를 얻어맞고 첫 실점했다.",
        "sentenceSize": 79
      },
      {
        "sentenceNo": 9,
        "sentenceContent": "이어 4회말에는 2사에서 김하성에게 밋밋한 체인지업을 던졌으나 중월 솔로포를 허용했다.",
        "sentenceSize": 48
      },
      {
        "sentenceNo": 10,
        "sentenceContent": "5회 마운드에 오른 유희관은 첫 타자 박병호에게 좌전 안타를 맞은 뒤 노경은으로 교체됐다.",
        "sentenceSize": 50
      },
      {
        "sentenceNo": 11,
        "sentenceContent": "이날 유희관은 넥센 타선에 무려 7피안타(2피홈런)를 내줬다.",
        "sentenceSize": 34
      },
      {
        "sentenceNo": 12,
        "sentenceContent": "볼넷은 3개. 5회 이어 던진 노경은이 계속된 1사 1,3루의 위기에서 김민성에게 좌익수 희생플라이를 헌납했고, 유희관의 실점은 3점이 됐다.",
        "sentenceSize": 79
      },
      {
        "sentenceNo": 13,
        "sentenceContent": "오후 9시 현재 넥센이 5-0으로 앞서고 있으며, 현재 두산은 오현택이 바통을 이어받았다. '넥센 두산 준플레이오프 3차전' '유희관 조기 강판' 온라인 중앙일보",
        "sentenceSize": 90
      }
    ]
  },
  "labeledDataInfo": {
    "newTitle": "큰 우려 속에 등판한 이 선수, 하지만 홈런포 두 방에 조기 강판!",
    "clickbaitClass": 0,
    "referSentenceInfo": [
      {
        "sentenceNo": 1,
        "referSentenceyn": "Y"
      },
      {
        "sentenceNo": 2,
        "referSentenceyn": "N"
      },
      {
        "sentenceNo": 3,
        "referSentenceyn": "Y"
      },
      {
        "sentenceNo": 4,
        "referSentenceyn": "N"
      },
      {
        "sentenceNo": 5,
        "referSentenceyn": "N"
      },
      {
        "sentenceNo": 6,
        "referSentenceyn": "N"
      },
      {
        "sentenceNo": 7,
        "referSentenceyn": "N"
      },
      {
        "sentenceNo": 8,
        "referSentenceyn": "N"
      },
      {
        "sentenceNo": 9,
        "referSentenceyn": "N"
      },
      {
        "sentenceNo": 10,
        "referSentenceyn": "N"
      },
      {
        "sentenceNo": 11,
        "referSentenceyn": "N"
      },
      {
        "sentenceNo": 12,
        "referSentenceyn": "N"
      },
      {
        "sentenceNo": 13,
        "referSentenceyn": "N"
      }
    ]
  }
}