{
  "sourceDataInfo": {
    "newsID": "ET_M03_165186",
    "newsCategory": "연예",
    "newsSubcategory": "영화",
    "newsTitle": "[ONE SHOT] 흥행 돌풍 ‘어벤져스3’ 최고 인기 캐릭터는?",
    "newsSubTitle": "",
    "newsContent": "마블 스튜디오의 창립 10주년 기념작 ‘어벤져스: 인피니티워’가 세계적으로 역대급 흥행 기록을 세우며 관객몰이를 하고 있다.\n특히 개성 넘치는 캐릭터들은 어벤져스 시리즈의 흥행에 있어서 가장 중요한 포인트다.\n이번 시리즈에서는 10주년 기념작답게 마블의 슈퍼 히어로가 총출동해 영화에 등장한다.\n그렇다면 한국과 미국의 국민이 가장 사랑하는 마블 캐릭터는 누구일까?\n먼저 한국인들은 ‘아이언맨’을 1위로 꼽았다.\n이어서 2위 ‘스파이더맨’, 3위 ‘캡틴 아메리카’, 4위 ‘토르’, 5위 ‘닥터 스트레인지’ 순이었다.\n미국인들은 ‘스파이더맨’이 가장 좋아하는 캐릭터 1위에 올랐고, 이어서 한국인 인기 순위 톱 5에 없는 ‘헐크’가 2위에, 3위는 한국과 같은 ‘캡틴 아메리카’, 4위에는 한국인이 가장 좋아하는 캐릭터인 ‘아이언맨’, 한국인 선호도 4위인 ‘토르’는 5위에 올랐다.\n한국인 선호 5위인 ‘닥터 스트레인지’는 미국 인기 캐릭터 순위 14위에 올라 양국 영화 팬들의 취향을 드러냈다.",
    "partNum": "P1",
    "useType": 0,
    "processType": "D",
    "processPattern": "16",
    "processLevel": "상",
    "sentenceCount": 8,
    "sentenceInfo": [
      {
        "sentenceNo": 1,
        "sentenceContent": "마블 스튜디오의 창립 10주년 기념작 ‘어벤져스: 인피니티워’가 세계적으로 역대급 흥행 기록을 세우며 관객몰이를 하고 있다.",
        "sentenceSize": 69
      },
      {
        "sentenceNo": 2,
        "sentenceContent": "특히 개성 넘치는 캐릭터들은 어벤져스 시리즈의 흥행에 있어서 가장 중요한 포인트다.",
        "sentenceSize": 46
      },
      {
        "sentenceNo": 3,
        "sentenceContent": "이번 시리즈에서는 10주년 기념작답게 마블의 슈퍼 히어로가 총출동해 영화에 등장한다.",
        "sentenceSize": 47
      },
      {
        "sentenceNo": 4,
        "sentenceContent": "그렇다면 한국과 미국의 국민이 가장 사랑하는 마블 캐릭터는 누구일까?",
        "sentenceSize": 38
      },
      {
        "sentenceNo": 5,
        "sentenceContent": "먼저 한국인들은 ‘아이언맨’을 1위로 꼽았다.",
        "sentenceSize": 25
      },
      {
        "sentenceNo": 6,
        "sentenceContent": "이어서 2위 ‘스파이더맨’, 3위 ‘캡틴 아메리카’, 4위 ‘토르’, 5위 ‘닥터 스트레인지’ 순이었다.",
        "sentenceSize": 58
      },
      {
        "sentenceNo": 7,
        "sentenceContent": "미국인들은 ‘스파이더맨’이 가장 좋아하는 캐릭터 1위에 올랐고, 이어서 한국인 인기 순위 톱 5에 없는 ‘헐크’가 2위에, 3위는 한국과 같은 ‘캡틴 아메리카’, 4위에는 한국인이 가장 좋아하는 캐릭터인 ‘아이언맨’, 한국인 선호도 4위인 ‘토르’는 5위에 올랐다.",
        "sentenceSize": 148
      },
      {
        "sentenceNo": 8,
        "sentenceContent": "한국인 선호 5위인 ‘닥터 스트레인지’는 미국 인기 캐릭터 순위 14위에 올라 양국 영화 팬들의 취향을 드러냈다.",
        "sentenceSize": 63
      }
    ]
  },
  "labeledDataInfo": {
    "newTitle": "한국인이 가장 사랑하는 미국 캐릭터... 미국의 결과는 정반대",
    "clickbaitClass": 0,
    "referSentenceInfo": [
      {
        "sentenceNo": 1,
        "referSentenceyn": "N"
      },
      {
        "sentenceNo": 2,
        "referSentenceyn": "N"
      },
      {
        "sentenceNo": 3,
        "referSentenceyn": "N"
      },
      {
        "sentenceNo": 4,
        "referSentenceyn": "Y"
      },
      {
        "sentenceNo": 5,
        "referSentenceyn": "Y"
      },
      {
        "sentenceNo": 6,
        "referSentenceyn": "N"
      },
      {
        "sentenceNo": 7,
        "referSentenceyn": "N"
      },
      {
        "sentenceNo": 8,
        "referSentenceyn": "N"
      }
    ]
  }
}