{
  "sourceDataInfo": {
    "newsID": "ET_M13_167314",
    "newsCategory": "연예",
    "newsSubcategory": "연예일반",
    "newsTitle": "70년대 인기 가족 밴드 ‘작은별 가족’ 꾸린 강문수 감독 별세, 향연 99세",
    "newsSubTitle": "",
    "newsContent": "1970년대 인기 가족 밴드 ‘작은별 가족’을 꾸린 감독 겸 제작자 강문수씨가 14일 별세했다.\n향년 99세. 유족 측은 고인이 이날 오전 숙환으로 세상을 떠났다고 언론에 전했다.\n1923년 함경남도 흥남에서 태어난 고인은 국내 최초 TV 방송인 HLKZ-TV를 비롯해 KBS, MBC, TBC 등에서 작가 겸 연출가로 일했고 1949년 ‘늙은광대’를 선보이며 영화감독으로 데뷔했다.\n975년 ‘사운드 오브 뮤직’을 표방한 가족 영화 ‘작은 별’이 인기를 끌면서 서울대 음대 성악과 출신인 아내 주영숙씨, 6남 1녀의 친자녀들과 함께 가족 밴드 ‘작은별 가족’을 결성했다.\n이듬해 TV 만화영화 주제곡 모음집을 발표하고 1977년에는 데뷔 음반을 내며 ‘나의 작은 꿈’등을 발표하며 큰 인기를 끌었다.\n당시 밴드에서 활동한 외동딸 강애리자는 1988년 솔로로 나서 ‘분홍 립스틱’을 히트시켰다.\n막내아들인 강인봉은 80년대 인기 록밴드 벌거숭이 프론트맨을 거쳐 포크그룹 자전거탄풍경에서 활동하고 있다.\n70년대 ‘유괴’, ‘레인보우’ 등을 연출한 고인은 80년대 공백기를 보내다가 1991년 복귀작 ‘어허 어이 어이 가리’로 대종상영화제 특별작품상을 받았다.\n이후에도 ‘불의 태양’(1994), ‘미친것들’(1997), ‘핫 썸머’(2002) 등 작품을 선보였다.\n작은별 문화센터 회장, 주식회사 작은 별 대표이사, 재단법인 한일문화협회 한국협회장 등을 역임했다.\n빈소는 서울 성동구 한양대학교병원 장례식장 8호실에 마련됐다.\n발인은 오는 16일 오전 5시 20분이며 장지는 남양주 천주교 신당동성당 소화묘원이다.",
    "partNum": "P1",
    "useType": 0,
    "processType": "D",
    "processPattern": "11",
    "processLevel": "하",
    "sentenceCount": 12,
    "sentenceInfo": [
      {
        "sentenceNo": 1,
        "sentenceContent": "1970년대 인기 가족 밴드 ‘작은별 가족’을 꾸린 감독 겸 제작자 강문수씨가 14일 별세했다.",
        "sentenceSize": 53
      },
      {
        "sentenceNo": 2,
        "sentenceContent": "향년 99세. 유족 측은 고인이 이날 오전 숙환으로 세상을 떠났다고 언론에 전했다.",
        "sentenceSize": 46
      },
      {
        "sentenceNo": 3,
        "sentenceContent": "1923년 함경남도 흥남에서 태어난 고인은 국내 최초 TV 방송인 HLKZ-TV를 비롯해 KBS, MBC, TBC 등에서 작가 겸 연출가로 일했고 1949년 ‘늙은광대’를 선보이며 영화감독으로 데뷔했다.",
        "sentenceSize": 113
      },
      {
        "sentenceNo": 4,
        "sentenceContent": "975년 ‘사운드 오브 뮤직’을 표방한 가족 영화 ‘작은 별’이 인기를 끌면서 서울대 음대 성악과 출신인 아내 주영숙씨, 6남 1녀의 친자녀들과 함께 가족 밴드 ‘작은별 가족’을 결성했다.",
        "sentenceSize": 105
      },
      {
        "sentenceNo": 5,
        "sentenceContent": "이듬해 TV 만화영화 주제곡 모음집을 발표하고 1977년에는 데뷔 음반을 내며 ‘나의 작은 꿈’등을 발표하며 큰 인기를 끌었다.",
        "sentenceSize": 71
      },
      {
        "sentenceNo": 6,
        "sentenceContent": "당시 밴드에서 활동한 외동딸 강애리자는 1988년 솔로로 나서 ‘분홍 립스틱’을 히트시켰다.",
        "sentenceSize": 51
      },
      {
        "sentenceNo": 7,
        "sentenceContent": "막내아들인 강인봉은 80년대 인기 록밴드 벌거숭이 프론트맨을 거쳐 포크그룹 자전거탄풍경에서 활동하고 있다.",
        "sentenceSize": 59
      },
      {
        "sentenceNo": 8,
        "sentenceContent": "70년대 ‘유괴’, ‘레인보우’ 등을 연출한 고인은 80년대 공백기를 보내다가 1991년 복귀작 ‘어허 어이 어이 가리’로 대종상영화제 특별작품상을 받았다.",
        "sentenceSize": 87
      },
      {
        "sentenceNo": 9,
        "sentenceContent": "이후에도 ‘불의 태양’(1994), ‘미친것들’(1997), ‘핫 썸머’(2002) 등 작품을 선보였다.",
        "sentenceSize": 58
      },
      {
        "sentenceNo": 10,
        "sentenceContent": "작은별 문화센터 회장, 주식회사 작은 별 대표이사, 재단법인 한일문화협회 한국협회장 등을 역임했다.",
        "sentenceSize": 55
      },
      {
        "sentenceNo": 11,
        "sentenceContent": "빈소는 서울 성동구 한양대학교병원 장례식장 8호실에 마련됐다.",
        "sentenceSize": 34
      },
      {
        "sentenceNo": 12,
        "sentenceContent": "발인은 오는 16일 오전 5시 20분이며 장지는 남양주 천주교 신당동성당 소화묘원이다.",
        "sentenceSize": 48
      }
    ]
  },
  "labeledDataInfo": {
    "newTitle": "99세로 세상 떠난 ‘작은별 가족' 강문수 씨, 별세 이유는?",
    "clickbaitClass": 0,
    "referSentenceInfo": [
      {
        "sentenceNo": 1,
        "referSentenceyn": "N"
      },
      {
        "sentenceNo": 2,
        "referSentenceyn": "N"
      },
      {
        "sentenceNo": 3,
        "referSentenceyn": "N"
      },
      {
        "sentenceNo": 4,
        "referSentenceyn": "N"
      },
      {
        "sentenceNo": 5,
        "referSentenceyn": "Y"
      },
      {
        "sentenceNo": 6,
        "referSentenceyn": "Y"
      },
      {
        "sentenceNo": 7,
        "referSentenceyn": "Y"
      },
      {
        "sentenceNo": 8,
        "referSentenceyn": "N"
      },
      {
        "sentenceNo": 9,
        "referSentenceyn": "N"
      },
      {
        "sentenceNo": 10,
        "referSentenceyn": "N"
      },
      {
        "sentenceNo": 11,
        "referSentenceyn": "N"
      },
      {
        "sentenceNo": 12,
        "referSentenceyn": "N"
      }
    ]
  }
}