{
  "sourceDataInfo": {
    "newsID": "ET_M13_167326",
    "newsCategory": "연예",
    "newsSubcategory": "방송",
    "newsTitle": "‘국대는 국대다’ 씨름 대통령 이만기의 귀환, 4.7% 후끈",
    "newsSubTitle": "",
    "newsContent": "“내 경기를 못 본 아들들에게 ‘아빠 열심히 살았다’는 걸 보여주고 싶어요.” MBN ‘국대는 국대다’가 80년대 ‘씨름 대통령’ 이만기의 2022년 선수 복귀 프로젝트를 선포하며 신선한 충격과 뭉클한 감동을 선사했다.\n19일 방송한 MBN ‘국대는 국대다’ 3회는 평균 4.7%(닐슨미디어 유료방송가구 2부 기준)의 시청률을 기록, 쾌속 질주를 이어나갔다.\n이날 방송에서는 천하장사만 10회, 총 장사 타이틀 49회, 평균 승률 84.7%에 빛나는 이만기가 씨름판으로 복귀를 선언, 본격적인 트레이닝에 돌입하는 모습이 펼쳐져 손에 땀을 쥐게 했다.\n먼저 “초대 천하장사 생중계 시청률 61%, 한 해 최고 승률 97%를 기록한 씨름계의 대통령”이라는 소개로 이만기가 ‘국대는 국대다’ 스튜디오에 등장했다.\n이만기는 다섯 페이스메이커 전현무-배성재-홍현희-김동현-김민아와 함께 ‘스타 이만기’의 탄생을 알린 초대 천하장사 경기를 시청했고, “이전까지 개인전 우승을 단 한 번도 못 했다, 다시 봐도 내 몸에 다른 사람이 들어와서 경기를 한 느낌”이라고 털어놨다.\n힘이 아닌 ‘기술 씨름’으로 모래판을 호령했다는 이만기는 “길거리를 다닐 수가 없을 정도로 전 연령층의 인기를 얻었다”며, “덕분에 중매도 많이 들어왔지만, 확고한 ‘자만추’ 스타일이었다”고 밝혀 웃음을 자아냈다.\n이어 이만기는 이주일-조용필-선동열을 넘어 2년 동안 연예인-스포츠 스타 소득 1위를 기록할 정도로 엄청났던 수입을 공개했다.\n그러나 “당시에 강남 아파트를 샀느냐”는 전현무-홍현희의 질문에 “세금도 많이 냈고, 후배들의 훈련비도 지원하고, 주변 사람들도 챙겨주느라 남는 게 없었다”라고 점점 작아지는 목소리로 답해 ‘짠내웃음’을 유발했다.\n혜성처럼 등장한 씨름 후배 강호동과 ‘기 싸움’이 폭발했던 경기를 지켜본 뒤에는 “강호동은 씨름선수 중 가장 천부적인 몸을 가졌다”고 칭찬한 뒤, “후배 스타를 키우고 은퇴해야 한다는 사명감이 있었는데, 강호동이 등장하면서 명맥이 이어질 수 있겠다는 판단으로 은퇴를 결심했다”고 말했다.\n이후 이만기는 다섯 페이스메이커와 즉석에서 체격 테스트를 진행했다.\n측정 결과 이만기의 허벅지는 현역 때보다는 7cm 얇아졌지만 현역 UFC 선수 김동현과 동일한 64cm를 기록했다.\n트레이드마크인 ‘하트 장딴지’는 20대 시절과 똑같은 48cm이라 ‘충격’을 안겼다.\n김동현과의 씨름 대결에서도 손쉽게 2연승을 따냈다.\n무려 7초 만에 승리를 거머쥔 이만기의 모습에 전현무는 “희망을 봤다”며 기분 좋은 예감을 드러냈다.\n이 자리에서 이만기는 31년 만에 씨름판 복귀를 선언한 이유에 대해 “두 아들이 제가 은퇴한 뒤 태어나 제 경기를 본 적이 없다”며, “아들들에게 씨름의 진면모를 보여주고, 아버지로서 그 시절 얼마나 열심히 살았는지, 멋진 모습을 보여주고 싶다”고 밝혀 뭉클한 감동을 자아냈다.\n상대 선수로 태백장사를 2회 차지한 현역 최강 허선행이 지목되자, 이만기는 크게 당황했다.\n그러나 이내, “내가 노련미는 더 좋다. 다만 체력 면에서 떨어지기 때문에, 단기간에 체력을 끌어올려 보겠다”며 굳은 의지를 내비쳤다.\n본격적인 트레이닝에 돌입하기 전, 이만기는 선수 시절 동료인 한라장사 이승삼과 태백&금강장사 이희윤을 만나 “허선행과 경기를 할 것”이라고 깜짝 발표했다.\n잠시 코웃음 치던 이승삼과 이희윤은 “선행이가 워낙 박자가 빨라서 버거운 상대”라며 “첫 템포를 조심하라”고 조언했다.\n또한 “나이는 먹어도 마음이 늙은 것은 아니다”는 격려와 함께 ‘고기 만찬’을 대접했다.\n이만기는 “구관이 명관이라는 소리를 들을 수 있도록 최선을 다하겠다”고 다시 한번 각오를 다졌다.\n마지막으로 이만기는 현직 트레이너로 활동 중인 둘째 아들 이동훈 군과 만나 ‘선수 복귀’를 알렸다.\n동훈 군은 “잘못하다 다친다”며 극구 반대했다.\n이에 이만기는 ‘시합 승낙’과 ‘트레이닝’을 걸고 아들과 즉석 씨름 대결에 나섰다.\n115kg의 ‘장사 2세’ 동훈 군은 “이길 수 있을 것 같다”고 자신했으나, 아버지 이만기에게 ‘1.8초 컷’으로 패했다. “샅바를 잡아보니 현역 선수랑 해도 되겠다”는 아들의 승낙에 힘입어 이만기는 허선행과의 ‘역사적 대결’을 위한 한 달간의 트레이닝에 돌입했다.\n한 시대를 호령했던 이만기의 화려했던 과거와, ‘아빠’로서의 진심을 담은 진정성 넘치는 도전이 시청자들의 마음을 뜨겁게 만든 한 회였다.\n방송 후 시청자들은 “천하장사 이만기의 선수 복귀라니, 2022년에 벌어지는 일이 맞나요?”, “‘국국대’의 기획력, 대박입니다!”, “당시 연봉이 지금으로 따지면 80억 수준이었다니, 씨름의 인기가 어마무시했네요”, “강호동 씨와의 경기 비화와 ‘깝죽거리지 마라’ 유행어까지! 여전한 입담에 방송 내내 웃었네요”, “이만기 선수를 든든하게 지켜주는 그 시절 동료와 트레이너 아들, 다섯 페이스메이커의 지원까지! 허선행 선수와의 대결이 너무나 기대됩니다” 등 역대급 반응을 보냈다.\n한편 MBN ‘국대는 국대다’는 각 분야의 스포츠 ‘레전드’를 소환해, 현역 스포츠 국가대표 선수와 맞대결을 벌이는 초유의 스포츠 리얼리티 예능. 이만기와 허선행의 ‘세기의 대결’은 오는 26일(토) 밤 9시 20분 방송하는 ‘국대는 국대다’에서 만날 수 있다.",
    "partNum": "P1",
    "useType": 0,
    "processType": "D",
    "processPattern": "11",
    "processLevel": "하",
    "sentenceCount": 28,
    "sentenceInfo": [
      {
        "sentenceNo": 1,
        "sentenceContent": "“내 경기를 못 본 아들들에게 ‘아빠 열심히 살았다’는 걸 보여주고 싶어요.” MBN ‘국대는 국대다’가 80년대 ‘씨름 대통령’ 이만기의 2022년 선수 복귀 프로젝트를 선포하며 신선한 충격과 뭉클한 감동을 선사했다.",
        "sentenceSize": 122
      },
      {
        "sentenceNo": 2,
        "sentenceContent": "19일 방송한 MBN ‘국대는 국대다’ 3회는 평균 4.7%(닐슨미디어 유료방송가구 2부 기준)의 시청률을 기록, 쾌속 질주를 이어나갔다.",
        "sentenceSize": 77
      },
      {
        "sentenceNo": 3,
        "sentenceContent": "이날 방송에서는 천하장사만 10회, 총 장사 타이틀 49회, 평균 승률 84.7%에 빛나는 이만기가 씨름판으로 복귀를 선언, 본격적인 트레이닝에 돌입하는 모습이 펼쳐져 손에 땀을 쥐게 했다.",
        "sentenceSize": 106
      },
      {
        "sentenceNo": 4,
        "sentenceContent": "먼저 “초대 천하장사 생중계 시청률 61%, 한 해 최고 승률 97%를 기록한 씨름계의 대통령”이라는 소개로 이만기가 ‘국대는 국대다’ 스튜디오에 등장했다.",
        "sentenceSize": 87
      },
      {
        "sentenceNo": 5,
        "sentenceContent": "이만기는 다섯 페이스메이커 전현무-배성재-홍현희-김동현-김민아와 함께 ‘스타 이만기’의 탄생을 알린 초대 천하장사 경기를 시청했고, “이전까지 개인전 우승을 단 한 번도 못 했다, 다시 봐도 내 몸에 다른 사람이 들어와서 경기를 한 느낌”이라고 털어놨다.",
        "sentenceSize": 142
      },
      {
        "sentenceNo": 6,
        "sentenceContent": "힘이 아닌 ‘기술 씨름’으로 모래판을 호령했다는 이만기는 “길거리를 다닐 수가 없을 정도로 전 연령층의 인기를 얻었다”며, “덕분에 중매도 많이 들어왔지만, 확고한 ‘자만추’ 스타일이었다”고 밝혀 웃음을 자아냈다.",
        "sentenceSize": 119
      },
      {
        "sentenceNo": 7,
        "sentenceContent": "이어 이만기는 이주일-조용필-선동열을 넘어 2년 동안 연예인-스포츠 스타 소득 1위를 기록할 정도로 엄청났던 수입을 공개했다.",
        "sentenceSize": 70
      },
      {
        "sentenceNo": 8,
        "sentenceContent": "그러나 “당시에 강남 아파트를 샀느냐”는 전현무-홍현희의 질문에 “세금도 많이 냈고, 후배들의 훈련비도 지원하고, 주변 사람들도 챙겨주느라 남는 게 없었다”라고 점점 작아지는 목소리로 답해 ‘짠내웃음’을 유발했다.",
        "sentenceSize": 119
      },
      {
        "sentenceNo": 9,
        "sentenceContent": "혜성처럼 등장한 씨름 후배 강호동과 ‘기 싸움’이 폭발했던 경기를 지켜본 뒤에는 “강호동은 씨름선수 중 가장 천부적인 몸을 가졌다”고 칭찬한 뒤, “후배 스타를 키우고 은퇴해야 한다는 사명감이 있었는데, 강호동이 등장하면서 명맥이 이어질 수 있겠다는 판단으로 은퇴를 결심했다”고 말했다.",
        "sentenceSize": 160
      },
      {
        "sentenceNo": 10,
        "sentenceContent": "이후 이만기는 다섯 페이스메이커와 즉석에서 체격 테스트를 진행했다.",
        "sentenceSize": 37
      },
      {
        "sentenceNo": 11,
        "sentenceContent": "측정 결과 이만기의 허벅지는 현역 때보다는 7cm 얇아졌지만 현역 UFC 선수 김동현과 동일한 64cm를 기록했다.",
        "sentenceSize": 64
      },
      {
        "sentenceNo": 12,
        "sentenceContent": "트레이드마크인 ‘하트 장딴지’는 20대 시절과 똑같은 48cm이라 ‘충격’을 안겼다.",
        "sentenceSize": 47
      },
      {
        "sentenceNo": 13,
        "sentenceContent": "김동현과의 씨름 대결에서도 손쉽게 2연승을 따냈다.",
        "sentenceSize": 28
      },
      {
        "sentenceNo": 14,
        "sentenceContent": "무려 7초 만에 승리를 거머쥔 이만기의 모습에 전현무는 “희망을 봤다”며 기분 좋은 예감을 드러냈다.",
        "sentenceSize": 56
      },
      {
        "sentenceNo": 15,
        "sentenceContent": "이 자리에서 이만기는 31년 만에 씨름판 복귀를 선언한 이유에 대해 “두 아들이 제가 은퇴한 뒤 태어나 제 경기를 본 적이 없다”며, “아들들에게 씨름의 진면모를 보여주고, 아버지로서 그 시절 얼마나 열심히 살았는지, 멋진 모습을 보여주고 싶다”고 밝혀 뭉클한 감동을 자아냈다.",
        "sentenceSize": 155
      },
      {
        "sentenceNo": 16,
        "sentenceContent": "상대 선수로 태백장사를 2회 차지한 현역 최강 허선행이 지목되자, 이만기는 크게 당황했다.",
        "sentenceSize": 50
      },
      {
        "sentenceNo": 17,
        "sentenceContent": "그러나 이내, “내가 노련미는 더 좋다. 다만 체력 면에서 떨어지기 때문에, 단기간에 체력을 끌어올려 보겠다”며 굳은 의지를 내비쳤다.",
        "sentenceSize": 75
      },
      {
        "sentenceNo": 18,
        "sentenceContent": "본격적인 트레이닝에 돌입하기 전, 이만기는 선수 시절 동료인 한라장사 이승삼과 태백&금강장사 이희윤을 만나 “허선행과 경기를 할 것”이라고 깜짝 발표했다.",
        "sentenceSize": 86
      },
      {
        "sentenceNo": 19,
        "sentenceContent": "잠시 코웃음 치던 이승삼과 이희윤은 “선행이가 워낙 박자가 빨라서 버거운 상대”라며 “첫 템포를 조심하라”고 조언했다.",
        "sentenceSize": 66
      },
      {
        "sentenceNo": 20,
        "sentenceContent": "또한 “나이는 먹어도 마음이 늙은 것은 아니다”는 격려와 함께 ‘고기 만찬’을 대접했다.",
        "sentenceSize": 49
      },
      {
        "sentenceNo": 21,
        "sentenceContent": "이만기는 “구관이 명관이라는 소리를 들을 수 있도록 최선을 다하겠다”고 다시 한번 각오를 다졌다.",
        "sentenceSize": 54
      },
      {
        "sentenceNo": 22,
        "sentenceContent": "마지막으로 이만기는 현직 트레이너로 활동 중인 둘째 아들 이동훈 군과 만나 ‘선수 복귀’를 알렸다.",
        "sentenceSize": 55
      },
      {
        "sentenceNo": 23,
        "sentenceContent": "동훈 군은 “잘못하다 다친다”며 극구 반대했다.",
        "sentenceSize": 26
      },
      {
        "sentenceNo": 24,
        "sentenceContent": "이에 이만기는 ‘시합 승낙’과 ‘트레이닝’을 걸고 아들과 즉석 씨름 대결에 나섰다.",
        "sentenceSize": 46
      },
      {
        "sentenceNo": 25,
        "sentenceContent": "115kg의 ‘장사 2세’ 동훈 군은 “이길 수 있을 것 같다”고 자신했으나, 아버지 이만기에게 ‘1.8초 컷’으로 패했다. “샅바를 잡아보니 현역 선수랑 해도 되겠다”는 아들의 승낙에 힘입어 이만기는 허선행과의 ‘역사적 대결’을 위한 한 달간의 트레이닝에 돌입했다.",
        "sentenceSize": 149
      },
      {
        "sentenceNo": 26,
        "sentenceContent": "한 시대를 호령했던 이만기의 화려했던 과거와, ‘아빠’로서의 진심을 담은 진정성 넘치는 도전이 시청자들의 마음을 뜨겁게 만든 한 회였다.",
        "sentenceSize": 76
      },
      {
        "sentenceNo": 27,
        "sentenceContent": "방송 후 시청자들은 “천하장사 이만기의 선수 복귀라니, 2022년에 벌어지는 일이 맞나요?”, “‘국국대’의 기획력, 대박입니다!”, “당시 연봉이 지금으로 따지면 80억 수준이었다니, 씨름의 인기가 어마무시했네요”, “강호동 씨와의 경기 비화와 ‘깝죽거리지 마라’ 유행어까지! 여전한 입담에 방송 내내 웃었네요”, “이만기 선수를 든든하게 지켜주는 그 시절 동료와 트레이너 아들, 다섯 페이스메이커의 지원까지! 허선행 선수와의 대결이 너무나 기대됩니다” 등 역대급 반응을 보냈다.",
        "sentenceSize": 269
      },
      {
        "sentenceNo": 28,
        "sentenceContent": "한편 MBN ‘국대는 국대다’는 각 분야의 스포츠 ‘레전드’를 소환해, 현역 스포츠 국가대표 선수와 맞대결을 벌이는 초유의 스포츠 리얼리티 예능. 이만기와 허선행의 ‘세기의 대결’은 오는 26일(토) 밤 9시 20분 방송하는 ‘국대는 국대다’에서 만날 수 있다.",
        "sentenceSize": 146
      }
    ]
  },
  "labeledDataInfo": {
    "newTitle": "이만기, 2022년 선수 복귀 프로젝트 선포... 무슨 일?",
    "clickbaitClass": 0,
    "referSentenceInfo": [
      {
        "sentenceNo": 1,
        "referSentenceyn": "Y"
      },
      {
        "sentenceNo": 2,
        "referSentenceyn": "N"
      },
      {
        "sentenceNo": 3,
        "referSentenceyn": "N"
      },
      {
        "sentenceNo": 4,
        "referSentenceyn": "N"
      },
      {
        "sentenceNo": 5,
        "referSentenceyn": "N"
      },
      {
        "sentenceNo": 6,
        "referSentenceyn": "N"
      },
      {
        "sentenceNo": 7,
        "referSentenceyn": "N"
      },
      {
        "sentenceNo": 8,
        "referSentenceyn": "N"
      },
      {
        "sentenceNo": 9,
        "referSentenceyn": "N"
      },
      {
        "sentenceNo": 10,
        "referSentenceyn": "N"
      },
      {
        "sentenceNo": 11,
        "referSentenceyn": "N"
      },
      {
        "sentenceNo": 12,
        "referSentenceyn": "N"
      },
      {
        "sentenceNo": 13,
        "referSentenceyn": "N"
      },
      {
        "sentenceNo": 14,
        "referSentenceyn": "N"
      },
      {
        "sentenceNo": 15,
        "referSentenceyn": "Y"
      },
      {
        "sentenceNo": 16,
        "referSentenceyn": "N"
      },
      {
        "sentenceNo": 17,
        "referSentenceyn": "N"
      },
      {
        "sentenceNo": 18,
        "referSentenceyn": "N"
      },
      {
        "sentenceNo": 19,
        "referSentenceyn": "N"
      },
      {
        "sentenceNo": 20,
        "referSentenceyn": "N"
      },
      {
        "sentenceNo": 21,
        "referSentenceyn": "N"
      },
      {
        "sentenceNo": 22,
        "referSentenceyn": "N"
      },
      {
        "sentenceNo": 23,
        "referSentenceyn": "N"
      },
      {
        "sentenceNo": 24,
        "referSentenceyn": "N"
      },
      {
        "sentenceNo": 25,
        "referSentenceyn": "N"
      },
      {
        "sentenceNo": 26,
        "referSentenceyn": "N"
      },
      {
        "sentenceNo": 27,
        "referSentenceyn": "N"
      },
      {
        "sentenceNo": 28,
        "referSentenceyn": "N"
      }
    ]
  }
}