{
  "sourceDataInfo": {
    "newsID": "ET_M03_168253",
    "newsCategory": "연예",
    "newsSubcategory": "연예가화제",
    "newsTitle": "김민수, 윤빛가람에 '욕설 메시지' 논란…\\\"중국 토종인줄 알았다\\\"",
    "newsSubTitle": "",
    "newsContent": "축구선수 윤빛가람이 공개한 배우 김민수의 욕설 메시지가 논란이 되고 있다.\n윤빛가람은 17일 자신의 인스타그램에 \\\"이 글은 최근 '우리집 꿀단지'라는 드라마에 나온 연기자 김민수라는 사람의 글입니다. 여러분 어떻게 생각하시나요?\\\"라며 사진 한 장을 게재했다.\n메시지 내용을 캡처한 이 사진에는 “조선족들이랑 공놀이 열심히 해” “생긴 건 때놈같이 생겨가지고” 등 윤빛가람과 그가 속한 옌볜 푸더팀을 강도높게 조롱하는 내용이 담겨있다.\n논란이 되자 윤빛가람은 \\\"어느 선수든 누구하나 자기 팀 자기 팬들 욕하는데 기분 좋은 사람 없습니다\\\"라며 \\\"다른 의도 없습니다 제 팬들 욕하는 게 싫었을 뿐. 저라고 기분 좋을리가 있나요. 잘못 된건 바로 잡아야 된다고 생각했을 뿐입니다\\\"라고 밝히며 해당 글을 삭제했다.\n한편 현재 김민수의 인스타그램 계정은 비공개로 전환됐다.\n온라인 중앙일보 [사진 윤빛가람 인스타그램]",
    "partNum": "P1",
    "useType": 0,
    "processType": "D",
    "processPattern": "11",
    "processLevel": "하",
    "sentenceCount": 6,
    "sentenceInfo": [
      {
        "sentenceNo": 1,
        "sentenceContent": "축구선수 윤빛가람이 공개한 배우 김민수의 욕설 메시지가 논란이 되고 있다.",
        "sentenceSize": 41
      },
      {
        "sentenceNo": 2,
        "sentenceContent": "윤빛가람은 17일 자신의 인스타그램에 \\\"이 글은 최근 '우리집 꿀단지'라는 드라마에 나온 연기자 김민수라는 사람의 글입니다. 여러분 어떻게 생각하시나요?\\\"라며 사진 한 장을 게재했다.",
        "sentenceSize": 104
      },
      {
        "sentenceNo": 3,
        "sentenceContent": "메시지 내용을 캡처한 이 사진에는 “조선족들이랑 공놀이 열심히 해” “생긴 건 때놈같이 생겨가지고” 등 윤빛가람과 그가 속한 옌볜 푸더팀을 강도높게 조롱하는 내용이 담겨있다.",
        "sentenceSize": 97
      },
      {
        "sentenceNo": 4,
        "sentenceContent": "논란이 되자 윤빛가람은 \\\"어느 선수든 누구하나 자기 팀 자기 팬들 욕하는데 기분 좋은 사람 없습니다\\\"라며 \\\"다른 의도 없습니다 제 팬들 욕하는 게 싫었을 뿐. 저라고 기분 좋을리가 있나요. 잘못 된건 바로 잡아야 된다고 생각했을 뿐입니다\\\"라고 밝히며 해당 글을 삭제했다.",
        "sentenceSize": 155
      },
      {
        "sentenceNo": 5,
        "sentenceContent": "한편 현재 김민수의 인스타그램 계정은 비공개로 전환됐다.",
        "sentenceSize": 31
      },
      {
        "sentenceNo": 6,
        "sentenceContent": "온라인 중앙일보 [사진 윤빛가람 인스타그램]",
        "sentenceSize": 24
      }
    ]
  },
  "labeledDataInfo": {
    "newTitle": "배우 김민수의 윤빛가람 향한 '욕설·조롱 메시지 논란'... 대체 어땠길래?",
    "clickbaitClass": 0,
    "referSentenceInfo": [
      {
        "sentenceNo": 1,
        "referSentenceyn": "Y"
      },
      {
        "sentenceNo": 2,
        "referSentenceyn": "N"
      },
      {
        "sentenceNo": 3,
        "referSentenceyn": "N"
      },
      {
        "sentenceNo": 4,
        "referSentenceyn": "N"
      },
      {
        "sentenceNo": 5,
        "referSentenceyn": "N"
      },
      {
        "sentenceNo": 6,
        "referSentenceyn": "N"
      }
    ]
  }
}