{
  "sourceDataInfo": {
    "newsID": "ET_M03_168748",
    "newsCategory": "연예",
    "newsSubcategory": "연예가화제",
    "newsTitle": "동호, 결혼 반지 공개 \\\"많의 상의하고 준비했다\\\"",
    "newsSubTitle": "",
    "newsContent": "유키스 출신 동호(22)가 결혼 반지를 공개했다.\n동호는 1일 자신의 트위터를 통해 \\\"오랜만에 결혼 소식으로 인사 드리게 됐습니다. 축복해주시고 잘 살라고 응원해주신 분들께 다시 한번 진심으로 감사 드립니다. 행복하게 잘사는 모습 보여드리겠습니다\\\"라고 적었다.\n이어 \\\"반면에 어린 나이에 내린 결정이라 걱정하시는 분들이 많이 계신데 저희끼리 많이 상의했고 계획하고 준비한 것이고 나이가 많으나 적으나 행복한 결혼 생활을 하기 위해서는 서로 많이 노력해야 한다고 생각하기 때문에 어린 나이에 결혼해도 서로 잘 노력한다면 충분히 행복한 결혼생활 할 수 있을거라 생각합니다\\\"라고 말했다.\n동호는 자신의 여자친구에 대해 \\\"어디까지 공개할지에 대해서는 신부가 상처받지 않게 신중히 고민하고 있는 부분이라 상의 후 공개하겠습니다. 다른 자세한 사항은 웨딩촬영 이후 다시 말씀 드리겠습니다\\\"라고 밝혔다.\n또 동호는 결혼반지 사진을 공개하며 \\\"오늘 웨딩촬영 입니다. 오랜만에 촬영이라 떨리지만 예쁘게 잘 나왔으면\\\"이라고 덧붙였다.\n한편 2년 전 아이돌 그룹 유키스를 떠난 동호는 28일 한살 연상의 연인과 결혼식을 올린다.",
    "partNum": "P1",
    "useType": 0,
    "processType": "D",
    "processPattern": "11",
    "processLevel": "하",
    "sentenceCount": 6,
    "sentenceInfo": [
      {
        "sentenceNo": 1,
        "sentenceContent": "유키스 출신 동호(22)가 결혼 반지를 공개했다.",
        "sentenceSize": 27
      },
      {
        "sentenceNo": 2,
        "sentenceContent": "동호는 1일 자신의 트위터를 통해 \\\"오랜만에 결혼 소식으로 인사 드리게 됐습니다. 축복해주시고 잘 살라고 응원해주신 분들께 다시 한번 진심으로 감사 드립니다. 행복하게 잘사는 모습 보여드리겠습니다\\\"라고 적었다.",
        "sentenceSize": 119
      },
      {
        "sentenceNo": 3,
        "sentenceContent": "이어 \\\"반면에 어린 나이에 내린 결정이라 걱정하시는 분들이 많이 계신데 저희끼리 많이 상의했고 계획하고 준비한 것이고 나이가 많으나 적으나 행복한 결혼 생활을 하기 위해서는 서로 많이 노력해야 한다고 생각하기 때문에 어린 나이에 결혼해도 서로 잘 노력한다면 충분히 행복한 결혼생활 할 수 있을거라 생각합니다\\\"라고 말했다.",
        "sentenceSize": 181
      },
      {
        "sentenceNo": 4,
        "sentenceContent": "동호는 자신의 여자친구에 대해 \\\"어디까지 공개할지에 대해서는 신부가 상처받지 않게 신중히 고민하고 있는 부분이라 상의 후 공개하겠습니다. 다른 자세한 사항은 웨딩촬영 이후 다시 말씀 드리겠습니다\\\"라고 밝혔다.",
        "sentenceSize": 118
      },
      {
        "sentenceNo": 5,
        "sentenceContent": "또 동호는 결혼반지 사진을 공개하며 \\\"오늘 웨딩촬영 입니다. 오랜만에 촬영이라 떨리지만 예쁘게 잘 나왔으면\\\"이라고 덧붙였다.",
        "sentenceSize": 71
      },
      {
        "sentenceNo": 6,
        "sentenceContent": "한편 2년 전 아이돌 그룹 유키스를 떠난 동호는 28일 한살 연상의 연인과 결혼식을 올린다.",
        "sentenceSize": 51
      }
    ]
  },
  "labeledDataInfo": {
    "newTitle": "유키스 출신 동호 결혼반지 공개했다, 동호의 피앙새는 누구?",
    "clickbaitClass": 0,
    "referSentenceInfo": [
      {
        "sentenceNo": 1,
        "referSentenceyn": "N"
      },
      {
        "sentenceNo": 2,
        "referSentenceyn": "N"
      },
      {
        "sentenceNo": 3,
        "referSentenceyn": "N"
      },
      {
        "sentenceNo": 4,
        "referSentenceyn": "N"
      },
      {
        "sentenceNo": 5,
        "referSentenceyn": "N"
      },
      {
        "sentenceNo": 6,
        "referSentenceyn": "Y"
      }
    ]
  }
}